tgficbot/__init__.py
tgficbot/constants.py
tgficbot/db.py
tgficbot/i18n.py
tgficbot/main.py
tgficbot/push_message.py
tgficbot/states.py
tgficbot/locales/en/LC_MESSAGES/main.mo
tgficbot/locales/zh-hans/LC_MESSAGES/main.mo
tgficbot/locales/zh-hant/LC_MESSAGES/main.mo
telegram_find_in_channel_bot-0.5.2.dist-info/LICENSE
telegram_find_in_channel_bot-0.5.2.dist-info/METADATA
telegram_find_in_channel_bot-0.5.2.dist-info/WHEEL
telegram_find_in_channel_bot-0.5.2.dist-info/entry_points.txt
telegram_find_in_channel_bot-0.5.2.dist-info/top_level.txt
telegram_find_in_channel_bot-0.5.2.dist-info/RECORD
