Metadata-Version: 2.1
Name: telegram-find-in-channel-bot
Version: 0.5.2
Summary: UNKNOWN
Home-page: https://github.com/chuangzhu/telegram-find-in-channel-bot
Author: Zhu Chuang
Author-email: genelocated@yandex.com
License: UNKNOWN
Platform: UNKNOWN
Requires-Python: >=3.7
License-File: LICENSE
Requires-Dist: telethon (>=1.17.0<1.24.0)
